[{"name":"vc.builder.install","duration":716351,"timestamp":396054751891,"id":"8159becc-93eb-4328-8d18-1b00b429a3da","parentId":"b32c9574-0455-4b97-b76c-1dad98725181","tags":{"cliType":"npm","lockfileVersion":"3"},"startTime":1773822342448},{"name":"vc.builder.build","duration":13133338,"timestamp":396055469747,"id":"6b46ef45-db6e-45b5-b3a1-6d4ba30f8dc2","parentId":"b32c9574-0455-4b97-b76c-1dad98725181","tags":{"buildScriptName":"build"},"startTime":1773822343166},{"name":"vc.builder","duration":20292621,"timestamp":396054743881,"id":"b32c9574-0455-4b97-b76c-1dad98725181","parentId":"2357a95b-db94-495e-8aa4-05a2efde9300","tags":{"builder.name":"@vercel/next","builder.version":"4.16.1","builder.dynamicallyInstalled":"false","install":"true","build":"true"},"startTime":1773822342440},{"name":"vc.builder.diagnostics","duration":603,"timestamp":396075036583,"id":"1c69315c-4496-4c04-a643-65c793a8e6f4","parentId":"b32c9574-0455-4b97-b76c-1dad98725181","tags":{},"startTime":1773822362733},{"name":"vc.builder.writeBuildResult","duration":129381,"timestamp":396075037243,"id":"fad2b840-8477-4750-bc59-0c75d4708204","parentId":"b32c9574-0455-4b97-b76c-1dad98725181","tags":{"buildOutputLength":"1"},"startTime":1773822362734},{"name":"vc.doBuild","duration":20498791,"timestamp":396054679801,"id":"2357a95b-db94-495e-8aa4-05a2efde9300","parentId":"eff449ec-bc73-402b-a65c-fbe5da8c74b3","tags":{},"startTime":1773822342376},{"name":"vc","duration":20507011,"timestamp":396054671591,"id":"eff449ec-bc73-402b-a65c-fbe5da8c74b3","tags":{},"startTime":1773822342368}]