{
  "type": "Prerender",
  "expiration": false,
  "group": 11,
  "bypassToken": "dca6ac68f1f9658973c14a1a2eba5e9a",
  "fallback": {
    "type": "FileFsRef",
    "mode": 33188,
    "fsPath": "_full.segment.rsc.prerender-fallback.rsc"
  },
  "initialHeaders": {
    "x-nextjs-stale-time": "300",
    "x-nextjs-prerender": "1",
    "x-next-cache-tags": "_N_T_/layout,_N_T_/writings/layout,_N_T_/writings/[slug]/layout,_N_T_/writings/[slug]/page,_N_T_/writings/ticket-watch",
    "vary": "rsc, next-router-state-tree, next-router-prefetch, next-router-segment-prefetch",
    "content-type": "text/x-component",
    "x-nextjs-postponed": "2"
  },
  "allowQuery": [],
  "allowHeader": [
    "host",
    "x-matched-path",
    "x-prerender-revalidate",
    "x-prerender-revalidate-if-generated",
    "x-next-revalidated-tags",
    "x-next-revalidate-tag-token"
  ]
}
